wheel_factorize/__init__.py
wheel_factorize-1.0.1.dist-info/METADATA
wheel_factorize-1.0.1.dist-info/RECORD
wheel_factorize-1.0.1.dist-info/WHEEL
wheel_factorize-1.0.1.dist-info/top_level.txt
