Metadata-Version: 2.1
Name: wheel-factorize
Version: 1.0.1
Summary: Library for finding prime factorizations and primality
Home-page: https://github.com/mcastorina/wheel-factorization
Author: miccah
Author-email: m.castorina93@gmail.com
License: UNKNOWN
Platform: UNKNOWN
Classifier: Programming Language :: Python :: 3
Classifier: Programming Language :: Python :: 2
Classifier: License :: OSI Approved :: GNU General Public License v3 (GPLv3)
Classifier: Operating System :: OS Independent
